<?xml version="1.0" encoding="utf-8" ?><dwsync><file name="gigpress-bg_BG.mo" server="ftp.akronfamily.com" local="3376970220" remote="11969492492" /><file name="gigpress-bg_BG.po" server="ftp.akronfamily.com" local="3376970220" remote="11969492492" /><file name="gigpress-de_DE.mo" server="ftp.akronfamily.com" local="3376970220" remote="11969492492" /><file name="gigpress-de_DE.po" server="ftp.akronfamily.com" local="3376970220" remote="11969492492" /><file name="gigpress-en_US.mo" server="ftp.akronfamily.com" local="3376970220" remote="11969492492" /><file name="gigpress-en_US.pot" server="ftp.akronfamily.com" local="3376970220" remote="11969492492" /><file name="gigpress-es_ES.mo" server="ftp.akronfamily.com" local="3376970220" remote="11969492492" /><file name="gigpress-es_ES.po" server="ftp.akronfamily.com" local="3376970220" remote="11969492492" /><file name="gigpress-fr_FR.mo" server="ftp.akronfamily.com" local="3376970220" remote="11969492492" /><file name="gigpress-fr_FR.po" server="ftp.akronfamily.com" local="3376970220" remote="11969492552" /><file name="gigpress-he_IL.mo" server="ftp.akronfamily.com" local="3376970220" remote="11969492552" /><file name="gigpress-he_IL.po" server="ftp.akronfamily.com" local="3376970220" remote="11969492552" /><file name="gigpress-it_IT.mo" server="ftp.akronfamily.com" local="3376970220" remote="11969492552" /><file name="gigpress-it_IT.po" server="ftp.akronfamily.com" local="3376970220" remote="11969492552" /><file name="gigpress-nb_NO.mo" server="ftp.akronfamily.com" local="3376970220" remote="11969492552" /><file name="gigpress-nb_NO.po" server="ftp.akronfamily.com" local="3376970220" remote="11969492552" /><file name="gigpress-nl_NL.mo" server="ftp.akronfamily.com" local="3376970220" remote="11969492552" /><file name="gigpress-nl_NL.po" server="ftp.akronfamily.com" local="3376970220" remote="11969492552" /><file name="gigpress-pl_PL.mo" server="ftp.akronfamily.com" local="3376970220" remote="11969492552" /><file name="gigpress-pl_PL.po" server="ftp.akronfamily.com" local="3376970220" remote="11969492552" /><file name="gigpress-pt_BR.mo" server="ftp.akronfamily.com" local="3376970220" remote="11969492552" /><file name="gigpress-pt_BR.po" server="ftp.akronfamily.com" local="3376970220" remote="11969492552" /><file name="gigpress-ru_RU.mo" server="ftp.akronfamily.com" local="3376970220" remote="11969492552" /><file name="gigpress-ru_RU.po" server="ftp.akronfamily.com" local="3376970220" remote="11969492552" /><file name="gigpress-sv_SE.mo" server="ftp.akronfamily.com" local="3376970220" remote="11969492552" /><file name="gigpress-sv_SE.po" server="ftp.akronfamily.com" local="3376970220" remote="11969492552" /><file name="gigpress-zh_CN.mo" server="ftp.akronfamily.com" local="3376970220" remote="11969492552" /><file name="gigpress-zh_CN.po" server="ftp.akronfamily.com" local="3376970220" remote="11969492552" /></dwsync>